[
    {
        "properties": {
            "districts": [],
            "custom_layers": [
                {
                    "type": "Feature",
                    "properties": {
                        "area_circle_type": "join",
                        "id_city": 397
                    },
                    "geometry": {
                        "type": "Polygon",
                        "coordinates": [
                            [
                                [
                                    -47.928965,
                                    -15.737138
                                ],
                                [
                                    -47.900466,
                                    -15.728216
                                ],
                                [
                                    -47.885358,
                                    -15.734825
                                ],
                                [
                                    -47.874714,
                                    -15.742095
                                ],
                                [
                                    -47.868533,
                                    -15.752669
                                ],
                                [
                                    -47.863383,
                                    -15.759277
                                ],
                                [
                                    -47.856172,
                                    -15.763903
                                ],
                                [
                                    -47.850335,
                                    -15.774806
                                ],
                                [
                                    -47.86098,
                                    -15.779432
                                ],
                                [
                                    -47.856172,
                                    -15.782736
                                ],
                                [
                                    -47.843125,
                                    -15.78637
                                ],
                                [
                                    -47.828704,
                                    -15.789343
                                ],
                                [
                                    -47.825613,
                                    -15.79562
                                ],
                                [
                                    -47.82836,
                                    -15.80487
                                ],
                                [
                                    -47.82836,
                                    -15.81445
                                ],
                                [
                                    -47.830077,
                                    -15.823368
                                ],
                                [
                                    -47.846902,
                                    -15.833938
                                ],
                                [
                                    -47.854799,
                                    -15.840544
                                ],
                                [
                                    -47.866817,
                                    -15.849461
                                ],
                                [
                                    -47.871967,
                                    -15.855076
                                ],
                                [
                                    -47.888448,
                                    -15.863662
                                ],
                                [
                                    -47.90184,
                                    -15.866635
                                ],
                                [
                                    -47.927592,
                                    -15.864653
                                ],
                                [
                                    -47.94579,
                                    -15.867295
                                ],
                                [
                                    -47.953,
                                    -15.875221
                                ],
                                [
                                    -47.965018,
                                    -15.880174
                                ],
                                [
                                    -47.979439,
                                    -15.878853
                                ],
                                [
                                    -48.002444,
                                    -15.880174
                                ],
                                [
                                    -48.02751,
                                    -15.877202
                                ],
                                [
                                    -48.014462,
                                    -15.846159
                                ],
                                [
                                    -48.020986,
                                    -15.83592
                                ],
                                [
                                    -48.020642,
                                    -15.823699
                                ],
                                [
                                    -48.023046,
                                    -15.810155
                                ],
                                [
                                    -48.018239,
                                    -15.790665
                                ],
                                [
                                    -48.015149,
                                    -15.777449
                                ],
                                [
                                    -48.011028,
                                    -15.764234
                                ],
                                [
                                    -48.009312,
                                    -15.758286
                                ],
                                [
                                    -48.005191,
                                    -15.754982
                                ],
                                [
                                    -47.958837,
                                    -15.746721
                                ],
                                [
                                    -47.941669,
                                    -15.742756
                                ],
                                [
                                    -47.933085,
                                    -15.740112
                                ],
                                [
                                    -47.928965,
                                    -15.738129
                                ],
                                [
                                    -47.928965,
                                    -15.737138
                                ]
                            ]
                        ]
                    }
                }
            ],
            "id_store_district": 3371687,
            "order": 0,
            "desc_store_district": "Região atendida",
            "id_city": 1562,
            "type": "default",
            "id": 1724088019347,
            "style": {
                "color": "#4CAF50",
                "fillColor": "#4CAF50"
            },
            "id_store_area": 78342,
            "id_store": 17009
        },
        "geometry": {
            "type": "Polygon",
            "coordinates": [
                [
                    [
                        -47.928965,
                        -15.737138
                    ],
                    [
                        -47.900466,
                        -15.728216
                    ],
                    [
                        -47.885358,
                        -15.734825
                    ],
                    [
                        -47.874714,
                        -15.742095
                    ],
                    [
                        -47.868533,
                        -15.752669
                    ],
                    [
                        -47.863383,
                        -15.759277
                    ],
                    [
                        -47.856172,
                        -15.763903
                    ],
                    [
                        -47.850598447,
                        -15.774313903
                    ],
                    [
                        -47.850404272,
                        -15.774836104
                    ],
                    [
                        -47.86098,
                        -15.779432
                    ],
                    [
                        -47.856172,
                        -15.782736
                    ],
                    [
                        -47.847196026,
                        -15.785236091
                    ],
                    [
                        -47.846728,
                        -15.787034
                    ],
                    [
                        -47.845517,
                        -15.794891
                    ],
                    [
                        -47.845517,
                        -15.810758
                    ],
                    [
                        -47.846728,
                        -15.818615
                    ],
                    [
                        -47.848734,
                        -15.826319
                    ],
                    [
                        -47.851515,
                        -15.833797
                    ],
                    [
                        -47.854850381,
                        -15.840582123
                    ],
                    [
                        -47.866817,
                        -15.849461
                    ],
                    [
                        -47.871967,
                        -15.855076
                    ],
                    [
                        -47.888448,
                        -15.863662
                    ],
                    [
                        -47.90184,
                        -15.866635
                    ],
                    [
                        -47.927592,
                        -15.864653
                    ],
                    [
                        -47.94579,
                        -15.867295
                    ],
                    [
                        -47.953,
                        -15.875221
                    ],
                    [
                        -47.959962739,
                        -15.878090566
                    ],
                    [
                        -47.96142,
                        -15.877589
                    ],
                    [
                        -47.968883,
                        -15.874194
                    ],
                    [
                        -47.975963,
                        -15.870112
                    ],
                    [
                        -47.982594,
                        -15.865382
                    ],
                    [
                        -47.98871,
                        -15.860049
                    ],
                    [
                        -47.994254,
                        -15.854166
                    ],
                    [
                        -47.999171,
                        -15.847787
                    ],
                    [
                        -48.003415,
                        -15.840976
                    ],
                    [
                        -48.006945,
                        -15.833797
                    ],
                    [
                        -48.009726,
                        -15.826319
                    ],
                    [
                        -48.011732,
                        -15.818615
                    ],
                    [
                        -48.012943,
                        -15.810758
                    ],
                    [
                        -48.013348,
                        -15.802825
                    ],
                    [
                        -48.012943,
                        -15.794891
                    ],
                    [
                        -48.011732,
                        -15.787034
                    ],
                    [
                        -48.009726,
                        -15.779328
                    ],
                    [
                        -48.006945,
                        -15.771849
                    ],
                    [
                        -48.003415,
                        -15.764667
                    ],
                    [
                        -47.999171,
                        -15.757853
                    ],
                    [
                        -47.995648851,
                        -15.753281441
                    ],
                    [
                        -47.958837,
                        -15.746721
                    ],
                    [
                        -47.941669,
                        -15.742756
                    ],
                    [
                        -47.933085,
                        -15.740112
                    ],
                    [
                        -47.928965,
                        -15.738129
                    ],
                    [
                        -47.928965,
                        -15.737138
                    ]
                ]
            ]
        },
        "type": "Feature"
    },
    {
        "properties": {
            "districts": [],
            "custom_layers": [],
            "id_store_district": 2845015,
            "order": 0,
            "desc_store_district": "Raios da loja 17009",
            "id_city": 1562,
            "type": "default",
            "id": 1689123637065,
            "style": {
                "color": "#4CAF50",
                "fillColor": "#4CAF50"
            },
            "radius_mode": [
                {
                    "radius": 3,
                    "id_store_district": 2845010,
                    "value_motoboy": 8.5,
                    "delivery_fee": 8.5
                },
                {
                    "radius": 5,
                    "id_store_district": 2845012,
                    "value_motoboy": 14,
                    "delivery_fee": 14
                },
                {
                    "radius": 4,
                    "id_store_district": 3288071,
                    "value_motoboy": 10,
                    "delivery_fee": 10
                },
                {
                    "radius": 1,
                    "id_store_district": 3371692,
                    "value_motoboy": 7.5,
                    "delivery_fee": 7.5
                },
                {
                    "radius": 10,
                    "id_store_district": 3371693,
                    "value_motoboy": 20,
                    "delivery_fee": 20
                }
            ],
            "id_store_area": 42370,
            "id_store": 17009
        },
        "geometry": {
            "type": "Point",
            "coordinates": [
                -15.802701,
                -47.929316
            ]
        },
        "type": "Feature"
    }
]